[
    {
        "title": "Semicenk-Yana-Yana-55",
        "artist": "Bilinmeyen Sanatçı",
        "file_path": "C:/Users/Yasir/Desktop/Semicenk-Yana-Yana-55.mp3",
        "duration": 147
    },
    {
        "title": "Semicenk-Pisman-Degilim-feat-Dogu-Swag-3",
        "artist": "Bilinmeyen Sanatçı",
        "file_path": "C:/Users/Yasir/Desktop/Semicenk-Pisman-Degilim-feat-Dogu-Swag-3.mp3",
        "duration": 142
    },
    {
        "title": "Semicenk-Batik-Gemi-10",
        "artist": "Bilinmeyen Sanatçı",
        "file_path": "C:/Users/Yasir/Desktop/Semicenk-Batik-Gemi-10.mp3",
        "duration": 258
    },
    {
        "title": "Canbay-Wolker-Dusmez-Kalkmaz-18",
        "artist": "Bilinmeyen Sanatçı",
        "file_path": "C:/Users/Yasir/Desktop/Canbay-Wolker-Dusmez-Kalkmaz-18.mp3",
        "duration": 155
    }
]